dca_ui/__init__.py
dca_ui/cli.py
databricks_cloud_automation-0.1.8.dist-info/LICENSE.txt
databricks_cloud_automation-0.1.8.dist-info/METADATA
databricks_cloud_automation-0.1.8.dist-info/WHEEL
databricks_cloud_automation-0.1.8.dist-info/entry_points.txt
databricks_cloud_automation-0.1.8.dist-info/top_level.txt
databricks_cloud_automation-0.1.8.dist-info/RECORD
